alibabacloud_dms_mcp_server/__init__.py
alibabacloud_dms_mcp_server/server.py
alibabacloud_dms_mcp_server-0.1.18.dist-info/METADATA
alibabacloud_dms_mcp_server-0.1.18.dist-info/WHEEL
alibabacloud_dms_mcp_server-0.1.18.dist-info/entry_points.txt
alibabacloud_dms_mcp_server-0.1.18.dist-info/licenses/LICENSE
alibabacloud_dms_mcp_server-0.1.18.dist-info/RECORD
