Metadata-Version: 2.4
Name: alibabacloud-dms-mcp-server
Version: 0.1.18
Summary: MCP Server for AlibabaCloud DMS
Author: AlibabaCloud DMS
License-Expression: Apache-2.0
License-File: LICENSE
Requires-Python: >=3.10
Requires-Dist: alibabacloud-dms-enterprise20181101>=1.76.0
Requires-Dist: httpx>=0.28.1
Requires-Dist: mcp[cli]>=1.8.1
Provides-Extra: dev
Requires-Dist: mypy>=1.15.0; extra == 'dev'
Requires-Dist: pytest-asyncio>=0.25.3; extra == 'dev'
Requires-Dist: pytest-cov>=6.0.0; extra == 'dev'
Requires-Dist: pytest-mock>=3.14.0; extra == 'dev'
Requires-Dist: pytest>=8.3.4; extra == 'dev'
Requires-Dist: ruff>=0.9.9; extra == 'dev'
